south_admin
